django_migration_checker/__init__.py
django_migration_checker/base.py
django_migration_checker/cli/__init__.py
django_migration_checker/cli/find_conflicts.py
django_migration_checker-0.8.0.dist-info/LICENSE
django_migration_checker-0.8.0.dist-info/METADATA
django_migration_checker-0.8.0.dist-info/WHEEL
django_migration_checker-0.8.0.dist-info/entry_points.txt
django_migration_checker-0.8.0.dist-info/top_level.txt
django_migration_checker-0.8.0.dist-info/RECORD
