Metadata-Version: 2.1
Name: django-migration-checker
Version: 0.8.0
Summary: Static migration conflict checker for Django
Home-page: https://github.com/tonyo/django-migration-checker
Author: Anton Ovchinnikov
Author-email: anton.ovchi2nikov@gmail.com
License: MIT license
Keywords: django_migration_checker
Platform: UNKNOWN
Classifier: Framework :: Django
Classifier: Intended Audience :: Developers
Classifier: License :: OSI Approved :: MIT License
Classifier: Natural Language :: English
Classifier: Programming Language :: Python :: 3
Classifier: Programming Language :: Python :: 3.6
Classifier: Programming Language :: Python :: 3.7
Classifier: Programming Language :: Python :: 3.8
Classifier: Programming Language :: Python :: 3.9
Classifier: Programming Language :: Python :: 3.10
